webquiz/__init__.py
webquiz/binary_entry.py
webquiz/build.py
webquiz/checker.py
webquiz/cli.py
webquiz/config.py
webquiz/server.py
webquiz/server_config.yaml.example
webquiz/templates/admin.html
webquiz/templates/files.html
webquiz/templates/index.html
webquiz/templates/live_stats.html
webquiz/templates/quiz_selection_required.html
webquiz/templates/template_error.html
webquiz/tunnel.py
webquiz-1.12.5.dist-info/METADATA
webquiz-1.12.5.dist-info/WHEEL
webquiz-1.12.5.dist-info/entry_points.txt
webquiz-1.12.5.dist-info/RECORD
