Metadata-Version: 2.1
Name: webquiz
Version: 1.12.5
Summary: A modern web-based quiz and testing system built with Python and aiohttp
Home-page: https://github.com/oduvan/webquiz
License: MIT
Keywords: quiz,testing,aiohttp,web,assessment,education
Author: Oleksandr Liabakh
Author-email: oduvan@gmail.com
Requires-Python: >=3.9,<3.15
Classifier: Development Status :: 4 - Beta
Classifier: Intended Audience :: Developers
Classifier: Intended Audience :: Education
Classifier: License :: OSI Approved :: MIT License
Classifier: Operating System :: OS Independent
Classifier: Programming Language :: Python :: 3
Classifier: Programming Language :: Python :: 3.9
Classifier: Programming Language :: Python :: 3.10
Classifier: Programming Language :: Python :: 3.11
Classifier: Programming Language :: Python :: 3.12
Classifier: Programming Language :: Python :: 3.13
Classifier: Programming Language :: Python :: 3.14
Classifier: Topic :: Education :: Testing
Classifier: Topic :: Internet :: WWW/HTTP :: HTTP Servers
Classifier: Topic :: Software Development :: Testing
Requires-Dist: PyYAML (>=6.0.2,<7.0.0)
Requires-Dist: aiofiles (>=24.1.0,<25.0.0)
Requires-Dist: aiohttp (>=3.12.13,<4.0.0)
Requires-Dist: asyncssh (>=2.14.0,<3.0.0)
Requires-Dist: cryptography (>=41.0.0,<42.0.0)
Requires-Dist: httpx (>=0.28.1,<0.29.0)
Project-URL: Bug Tracker, https://github.com/oduvan/webquiz/issues
Project-URL: Documentation, https://github.com/oduvan/webquiz
Project-URL: Repository, https://github.com/oduvan/webquiz
